zedsuite-0.0.7.dist-info/top_level.txt
zedsuite-0.0.7.dist-info/WHEEL
zedsuite-0.0.7.dist-info/METADATA
zedsuite-0.0.7.dist-info/RECORD
zedsuite.libs/libgslcblas-15b2d0fe.so.0.0.0
zedsuite.libs/libgsl-b885fd68.so.0.14.0
zedsuite.libs/libgomp-3300acd3.so.1.0.0
zedsuite/genesess.pyx
zedsuite/bootstrap.cpp
zedsuite/utils.py
zedsuite/bootstrap.pyx
zedsuite/quantizer.cpp
zedsuite/zutil.cpp
zedsuite/quantizer.pyx
zedsuite/genesess.cpp
zedsuite/zutil.pyx
zedsuite/bootstrap.cpython-39-x86_64-linux-gnu.so
zedsuite/__init__.py
